django_quanttide_projects/__init__.py
django_quanttide_projects/apps.py
django_quanttide_projects/models/__init__.py
django_quanttide_projects/models/choices.py
django_quanttide_projects/models/fields.py
django_quanttide_projects/models/models.py
django_quanttide_projects-0.1.0b1.dist-info/LICENSE
django_quanttide_projects-0.1.0b1.dist-info/METADATA
django_quanttide_projects-0.1.0b1.dist-info/WHEEL
django_quanttide_projects-0.1.0b1.dist-info/RECORD
