Metadata-Version: 2.1
Name: django-quanttide-projects
Version: 0.1.0b1
Summary: 量潮项目管理Django SDK
License: Apache 2.0
Author: QuantTide Inc.
Author-email: opensource@quanttide.com
Requires-Python: >=3.8,<4.0
Classifier: License :: Other/Proprietary License
Classifier: Programming Language :: Python :: 3
Classifier: Programming Language :: Python :: 3.8
Classifier: Programming Language :: Python :: 3.9
Classifier: Programming Language :: Python :: 3.10
Classifier: Programming Language :: Python :: 3.11
Requires-Dist: Django (>=3.1)
Requires-Dist: django-quanttide (>=0.1.0b1,<0.2.0)
Requires-Dist: djangorestframework (>=3.0)
